ctvx.cpython-39-x86_64-linux-gnu.so
gewel/_timekeeper.py
gewel/__init__.py
gewel/color.py
gewel/record.py
gewel/player.py
gewel/draw.py
gewel/contrib/chart.py
gewel/contrib/__init__.py
gewel/contrib/tvdraw.py
gewel/contrib/maps.py
tvx/types.py
tvx/__init__.py
tvx/utils.py
tvx/_tvd.py
Gewel-0.3.1.dist-info/RECORD
Gewel-0.3.1.dist-info/METADATA
Gewel-0.3.1.dist-info/WHEEL
Gewel-0.3.1.dist-info/LICENSE.md
Gewel-0.3.1.dist-info/top_level.txt
gewelversion/__init__.py
